piou/__init__.py
piou/cli.py
piou/command.py
piou/exceptions.py
piou/utils.py
piou/formatter/__init__.py
piou/formatter/base.py
piou/formatter/rich_formatter.py
piou/formatter/utils.py
piou/tui/__init__.py
piou/tui/app.py
piou/tui/cli.py
piou/tui/context.py
piou/tui/history.py
piou/tui/runner.py
piou/tui/suggester.py
piou/tui/utils.py
piou/tui/static/app.tcss
piou-0.28.4.dist-info/METADATA
piou-0.28.4.dist-info/WHEEL
piou-0.28.4.dist-info/licenses/LICENSE
piou-0.28.4.dist-info/RECORD
