Metadata-Version: 2.4
Name: piou
Version: 0.28.4
Summary: A CLI toolkit
Author-email: Julien Brayere <julien.brayere@obitrain.com>
License-Expression: MIT
License-File: LICENSE
Keywords: cli
Classifier: Environment :: Console
Classifier: Operating System :: OS Independent
Classifier: Programming Language :: Python :: 3 :: Only
Classifier: Programming Language :: Python :: 3.10
Classifier: Programming Language :: Python :: 3.11
Classifier: Programming Language :: Python :: 3.12
Classifier: Programming Language :: Python :: 3.13
Classifier: Programming Language :: Python :: 3.14
Requires-Python: >=3.10
Requires-Dist: rich<15.0,>=10.11.0
Requires-Dist: typing-extensions>=4.4.0
Provides-Extra: tui
Requires-Dist: textual>=0.40.0; extra == 'tui'
